[
  {
    "description": "",
    "elements": [
      {
        "description": "",
        "id": "contact;fill-out-contact-with-empty-name",
        "keyword": "Scenario",
        "line": 3,
        "name": "fill out contact with empty name",
        "steps": [
          {
            "keyword": "Before",
            "hidden": true,
            "result": {
              "status": "passed",
              "duration": 2276204446
            }
          },
          {
            "arguments": [],
            "keyword": "Given ",
            "line": 4,
            "name": "I navigate to spinmatic homepage",
            "match": {
              "location": "src/steps/contact _page_step.ts:5"
            },
            "result": {
              "status": "passed",
              "duration": 2026178644
            }
          },
          {
            "arguments": [],
            "keyword": "When ",
            "line": 5,
            "name": "I select Contact menu",
            "match": {
              "location": "src/steps/contact _page_step.ts:9"
            },
            "result": {
              "status": "failed",
              "duration": 5003299643,
              "error_message": "Error: function timed out, ensure the promise resolves within 5000 milliseconds\n    at Timeout.<anonymous> (/Users/reyescuesta/Documents/GitHubSami/e2e-playwright/node_modules/@cucumber/cucumber/src/time.ts:52:14)\n    at listOnTimeout (node:internal/timers:573:17)\n    at processTimers (node:internal/timers:514:7)"
            }
          },
          {
            "arguments": [],
            "keyword": "And ",
            "line": 6,
            "name": "I fill out name with \"\"",
            "match": {
              "location": "src/steps/contact _page_step.ts:18"
            },
            "result": {
              "status": "skipped",
              "duration": 0
            }
          },
          {
            "arguments": [],
            "keyword": "And ",
            "line": 7,
            "name": "I fill out email with \"samanta@gmail.com\"",
            "match": {
              "location": "src/steps/contact _page_step.ts:13"
            },
            "result": {
              "status": "skipped",
              "duration": 0
            }
          },
          {
            "arguments": [],
            "keyword": "When ",
            "line": 8,
            "name": "I press send mensage",
            "match": {
              "location": "src/steps/contact _page_step.ts:23"
            },
            "result": {
              "status": "skipped",
              "duration": 0
            }
          },
          {
            "arguments": [],
            "keyword": "Then ",
            "line": 9,
            "name": "the input name is mark as invalid",
            "match": {
              "location": "src/steps/contact _page_step.ts:27"
            },
            "result": {
              "status": "skipped",
              "duration": 0
            }
          },
          {
            "keyword": "After",
            "hidden": true,
            "result": {
              "status": "passed",
              "duration": 994333383
            }
          }
        ],
        "tags": [],
        "type": "scenario"
      },
      {
        "description": "",
        "id": "contact;email-invalid-format",
        "keyword": "Scenario",
        "line": 11,
        "name": "email invalid format",
        "steps": [
          {
            "keyword": "Before",
            "hidden": true,
            "result": {
              "status": "passed",
              "duration": 2074235541
            }
          },
          {
            "arguments": [],
            "keyword": "Given ",
            "line": 12,
            "name": "I navigate to spinmatic homepage",
            "match": {
              "location": "src/steps/contact _page_step.ts:5"
            },
            "result": {
              "status": "passed",
              "duration": 2025528150
            }
          },
          {
            "arguments": [],
            "keyword": "When ",
            "line": 13,
            "name": "I select Contact menu",
            "match": {
              "location": "src/steps/contact _page_step.ts:9"
            },
            "result": {
              "status": "failed",
              "duration": 5040541917,
              "error_message": "Error: function timed out, ensure the promise resolves within 5000 milliseconds\n    at Timeout.<anonymous> (/Users/reyescuesta/Documents/GitHubSami/e2e-playwright/node_modules/@cucumber/cucumber/src/time.ts:52:14)\n    at listOnTimeout (node:internal/timers:573:17)\n    at processTimers (node:internal/timers:514:7)"
            }
          },
          {
            "arguments": [],
            "keyword": "And ",
            "line": 14,
            "name": "I fill out name with \"Samanta\"",
            "match": {
              "location": "src/steps/contact _page_step.ts:18"
            },
            "result": {
              "status": "skipped",
              "duration": 0
            }
          },
          {
            "arguments": [],
            "keyword": "And ",
            "line": 15,
            "name": "I fill out email with \"FDSghjksASjjjDDDJJK\"",
            "match": {
              "location": "src/steps/contact _page_step.ts:13"
            },
            "result": {
              "status": "skipped",
              "duration": 0
            }
          },
          {
            "arguments": [],
            "keyword": "When ",
            "line": 16,
            "name": "I press send mensage",
            "match": {
              "location": "src/steps/contact _page_step.ts:23"
            },
            "result": {
              "status": "skipped",
              "duration": 0
            }
          },
          {
            "arguments": [],
            "keyword": "Then ",
            "line": 17,
            "name": "the input email is mark as invalid",
            "match": {
              "location": "src/steps/contact _page_step.ts:32"
            },
            "result": {
              "status": "skipped",
              "duration": 0
            }
          },
          {
            "keyword": "After",
            "hidden": true,
            "result": {
              "status": "passed",
              "duration": 1063319462
            }
          }
        ],
        "tags": [],
        "type": "scenario"
      }
    ],
    "id": "contact",
    "line": 1,
    "keyword": "Feature",
    "name": "Contact",
    "tags": [],
    "uri": "src/features/contact_page.feature"
  },
  {
    "description": "",
    "elements": [
      {
        "description": "",
        "id": "game;enter-game",
        "keyword": "Scenario",
        "line": 3,
        "name": "enter Game",
        "steps": [
          {
            "keyword": "Before",
            "hidden": true,
            "result": {
              "status": "passed",
              "duration": 2092633593
            }
          },
          {
            "arguments": [],
            "keyword": "Given ",
            "line": 4,
            "name": "I navigate to spinmatic homepage",
            "match": {
              "location": "src/steps/contact _page_step.ts:5"
            },
            "result": {
              "status": "passed",
              "duration": 1832495736
            }
          },
          {
            "arguments": [],
            "keyword": "When ",
            "line": 5,
            "name": "I select Game menu",
            "match": {
              "location": "src/steps/game_page.ts:4"
            },
            "result": {
              "status": "failed",
              "duration": 5005868596,
              "error_message": "Error: function timed out, ensure the promise resolves within 5000 milliseconds\n    at Timeout.<anonymous> (/Users/reyescuesta/Documents/GitHubSami/e2e-playwright/node_modules/@cucumber/cucumber/src/time.ts:52:14)\n    at listOnTimeout (node:internal/timers:573:17)\n    at processTimers (node:internal/timers:514:7)"
            }
          },
          {
            "arguments": [],
            "keyword": "Then ",
            "line": 6,
            "name": "I should see the title Game",
            "match": {
              "location": "src/steps/game_page.ts:8"
            },
            "result": {
              "status": "skipped",
              "duration": 0
            }
          },
          {
            "keyword": "After",
            "hidden": true,
            "result": {
              "status": "passed",
              "duration": 1335032772
            }
          }
        ],
        "tags": [],
        "type": "scenario"
      },
      {
        "description": "",
        "id": "game;play-game",
        "keyword": "Scenario",
        "line": 8,
        "name": "play game",
        "steps": [
          {
            "keyword": "Before",
            "hidden": true,
            "result": {
              "status": "passed",
              "duration": 2042667312
            }
          },
          {
            "arguments": [],
            "keyword": "Given ",
            "line": 9,
            "name": "I navigate to spinmatic homepage",
            "match": {
              "location": "src/steps/contact _page_step.ts:5"
            },
            "result": {
              "status": "passed",
              "duration": 1947657697
            }
          },
          {
            "arguments": [],
            "keyword": "When ",
            "line": 10,
            "name": "I select Game menu",
            "match": {
              "location": "src/steps/game_page.ts:4"
            },
            "result": {
              "status": "failed",
              "duration": 5003813812,
              "error_message": "Error: function timed out, ensure the promise resolves within 5000 milliseconds\n    at Timeout.<anonymous> (/Users/reyescuesta/Documents/GitHubSami/e2e-playwright/node_modules/@cucumber/cucumber/src/time.ts:52:14)\n    at listOnTimeout (node:internal/timers:573:17)\n    at processTimers (node:internal/timers:514:7)"
            }
          },
          {
            "arguments": [],
            "keyword": "When ",
            "line": 11,
            "name": "I press Plata o Plomo Deluxe",
            "match": {
              "location": "src/steps/game_page.ts:12"
            },
            "result": {
              "status": "skipped",
              "duration": 0
            }
          },
          {
            "arguments": [],
            "keyword": "When ",
            "line": 12,
            "name": "I press PLAY NOW",
            "match": {
              "location": "src/steps/game_page.ts:16"
            },
            "result": {
              "status": "skipped",
              "duration": 0
            }
          },
          {
            "arguments": [],
            "keyword": "Then ",
            "line": 13,
            "name": "I should see \"Are you over 18?This game requires you to be 18 years or older to playYesNo\"",
            "match": {
              "location": "src/steps/game_page.ts:20"
            },
            "result": {
              "status": "skipped",
              "duration": 0
            }
          },
          {
            "arguments": [],
            "keyword": "Then ",
            "line": 14,
            "name": "I press \"NO\"",
            "match": {
              "location": "src/steps/game_page.ts:24"
            },
            "result": {
              "status": "skipped",
              "duration": 0
            }
          },
          {
            "keyword": "After",
            "hidden": true,
            "result": {
              "status": "passed",
              "duration": 1023726311
            }
          }
        ],
        "tags": [],
        "type": "scenario"
      }
    ],
    "id": "game",
    "line": 1,
    "keyword": "Feature",
    "name": "Game",
    "tags": [],
    "uri": "src/features/game_page.feature"
  }
]