[
  {
    "description": "",
    "elements": [
      {
        "description": "",
        "id": "contact;fill-out-contact-with-empty-name",
        "keyword": "Scenario",
        "line": 3,
        "name": "fill out contact with empty name",
        "steps": [
          {
            "keyword": "Before",
            "hidden": true,
            "result": {
              "status": "passed",
              "duration": 759866615
            }
          },
          {
            "arguments": [],
            "keyword": "Given ",
            "line": 4,
            "name": "I navigate to spinmatic homepage",
            "match": {
              "location": "src/steps/contact _page_step.ts:5"
            },
            "result": {
              "status": "passed",
              "duration": 1918038682
            }
          },
          {
            "arguments": [],
            "keyword": "When ",
            "line": 5,
            "name": "I select Contact menu",
            "match": {
              "location": "src/steps/contact _page_step.ts:9"
            },
            "result": {
              "status": "passed",
              "duration": 1744977279
            }
          },
          {
            "arguments": [],
            "keyword": "And ",
            "line": 6,
            "name": "I fill out name with \"\"",
            "match": {
              "location": "src/steps/contact _page_step.ts:18"
            },
            "result": {
              "status": "passed",
              "duration": 796147482
            }
          },
          {
            "arguments": [],
            "keyword": "And ",
            "line": 7,
            "name": "I fill out email with \"samanta@gmail.com\"",
            "match": {
              "location": "src/steps/contact _page_step.ts:13"
            },
            "result": {
              "status": "passed",
              "duration": 69273685
            }
          },
          {
            "arguments": [],
            "keyword": "When ",
            "line": 8,
            "name": "I press send mensage",
            "match": {
              "location": "src/steps/contact _page_step.ts:23"
            },
            "result": {
              "status": "passed",
              "duration": 426758501
            }
          },
          {
            "arguments": [],
            "keyword": "Then ",
            "line": 9,
            "name": "the input name is mark as invalid",
            "match": {
              "location": "src/steps/contact _page_step.ts:27"
            },
            "result": {
              "status": "passed",
              "duration": 66201853
            }
          },
          {
            "keyword": "After",
            "hidden": true,
            "result": {
              "status": "passed",
              "duration": 1801816596
            }
          }
        ],
        "tags": [],
        "type": "scenario"
      },
      {
        "description": "",
        "id": "contact;email-invalid-format",
        "keyword": "Scenario",
        "line": 11,
        "name": "email invalid format",
        "steps": [
          {
            "keyword": "Before",
            "hidden": true,
            "result": {
              "status": "passed",
              "duration": 890024322
            }
          },
          {
            "arguments": [],
            "keyword": "Given ",
            "line": 12,
            "name": "I navigate to spinmatic homepage",
            "match": {
              "location": "src/steps/contact _page_step.ts:5"
            },
            "result": {
              "status": "passed",
              "duration": 1851244537
            }
          },
          {
            "arguments": [],
            "keyword": "When ",
            "line": 13,
            "name": "I select Contact menu",
            "match": {
              "location": "src/steps/contact _page_step.ts:9"
            },
            "result": {
              "status": "passed",
              "duration": 1571785072
            }
          },
          {
            "arguments": [],
            "keyword": "And ",
            "line": 14,
            "name": "I fill out name with \"Samanta\"",
            "match": {
              "location": "src/steps/contact _page_step.ts:18"
            },
            "result": {
              "status": "passed",
              "duration": 960120199
            }
          },
          {
            "arguments": [],
            "keyword": "And ",
            "line": 15,
            "name": "I fill out email with \"FDSghjksASjjjDDDJJK\"",
            "match": {
              "location": "src/steps/contact _page_step.ts:13"
            },
            "result": {
              "status": "passed",
              "duration": 472265695
            }
          },
          {
            "arguments": [],
            "keyword": "When ",
            "line": 16,
            "name": "I press send mensage",
            "match": {
              "location": "src/steps/contact _page_step.ts:23"
            },
            "result": {
              "status": "passed",
              "duration": 220897790
            }
          },
          {
            "arguments": [],
            "keyword": "Then ",
            "line": 17,
            "name": "the input email is mark as invalid",
            "match": {
              "location": "src/steps/contact _page_step.ts:32"
            },
            "result": {
              "status": "passed",
              "duration": 60150128
            }
          },
          {
            "keyword": "After",
            "hidden": true,
            "result": {
              "status": "passed",
              "duration": 2115955672
            }
          }
        ],
        "tags": [],
        "type": "scenario"
      }
    ],
    "id": "contact",
    "line": 1,
    "keyword": "Feature",
    "name": "Contact",
    "tags": [],
    "uri": "src/features/contact_page.feature"
  },
  {
    "description": "",
    "elements": [
      {
        "description": "",
        "id": "game;enter-game",
        "keyword": "Scenario",
        "line": 3,
        "name": "enter Game",
        "steps": [
          {
            "keyword": "Before",
            "hidden": true,
            "result": {
              "status": "passed",
              "duration": 707560276
            }
          },
          {
            "arguments": [],
            "keyword": "Given ",
            "line": 4,
            "name": "I navigate to spinmatic homepage",
            "match": {
              "location": "src/steps/contact _page_step.ts:5"
            },
            "result": {
              "status": "passed",
              "duration": 1234816842
            }
          },
          {
            "arguments": [],
            "keyword": "When ",
            "line": 5,
            "name": "I select Game menu",
            "match": {
              "location": "src/steps/game_page.ts:4"
            },
            "result": {
              "status": "passed",
              "duration": 1311134747
            }
          },
          {
            "arguments": [],
            "keyword": "Then ",
            "line": 6,
            "name": "I should see the title Game",
            "match": {
              "location": "src/steps/game_page.ts:8"
            },
            "result": {
              "status": "passed",
              "duration": 477531332
            }
          },
          {
            "keyword": "After",
            "hidden": true,
            "result": {
              "status": "passed",
              "duration": 833217566
            }
          }
        ],
        "tags": [],
        "type": "scenario"
      },
      {
        "description": "",
        "id": "game;play-game",
        "keyword": "Scenario",
        "line": 8,
        "name": "play game",
        "steps": [
          {
            "keyword": "Before",
            "hidden": true,
            "result": {
              "status": "passed",
              "duration": 538314803
            }
          },
          {
            "arguments": [],
            "keyword": "Given ",
            "line": 9,
            "name": "I navigate to spinmatic homepage",
            "match": {
              "location": "src/steps/contact _page_step.ts:5"
            },
            "result": {
              "status": "passed",
              "duration": 1905592075
            }
          },
          {
            "arguments": [],
            "keyword": "When ",
            "line": 10,
            "name": "I select Game menu",
            "match": {
              "location": "src/steps/game_page.ts:4"
            },
            "result": {
              "status": "passed",
              "duration": 999308806
            }
          },
          {
            "arguments": [],
            "keyword": "When ",
            "line": 11,
            "name": "I press Plata o Plomo Deluxe",
            "match": {
              "location": "src/steps/game_page.ts:12"
            },
            "result": {
              "status": "passed",
              "duration": 889012349
            }
          },
          {
            "arguments": [],
            "keyword": "When ",
            "line": 12,
            "name": "I press PLAY NOW",
            "match": {
              "location": "src/steps/game_page.ts:16"
            },
            "result": {
              "status": "passed",
              "duration": 481517886
            }
          },
          {
            "arguments": [],
            "keyword": "Then ",
            "line": 13,
            "name": "I should see \"Are you over 18?This game requires you to be 18 years or older to playYesNo\"",
            "match": {
              "location": "src/steps/game_page.ts:20"
            },
            "result": {
              "status": "passed",
              "duration": 71735121
            }
          },
          {
            "arguments": [],
            "keyword": "Then ",
            "line": 14,
            "name": "I press \"NO\"",
            "match": {
              "location": "src/steps/game_page.ts:24"
            },
            "result": {
              "status": "passed",
              "duration": 193440146
            }
          },
          {
            "arguments": [],
            "keyword": "Then ",
            "line": 15,
            "name": "I should see the title Plata o Plomo Deluxe",
            "match": {
              "location": "src/steps/game_page.ts:28"
            },
            "result": {
              "status": "passed",
              "duration": 7856476
            }
          },
          {
            "keyword": "After",
            "hidden": true,
            "result": {
              "status": "passed",
              "duration": 430329609
            }
          }
        ],
        "tags": [],
        "type": "scenario"
      }
    ],
    "id": "game",
    "line": 1,
    "keyword": "Feature",
    "name": "Game",
    "tags": [],
    "uri": "src/features/game_page.feature"
  }
]